tutor_contrib_codejail-21.0.0.dist-info/licenses/LICENSE
tutorcodejail/__about__.py
tutorcodejail/__init__.py
tutorcodejail/plugin.py
tutorcodejail/patches/.gitignore
tutorcodejail/patches/cms-env
tutorcodejail/patches/k8s-deployments
tutorcodejail/patches/k8s-services
tutorcodejail/patches/kustomization-configmapgenerator
tutorcodejail/patches/lms-env
tutorcodejail/patches/local-docker-compose-dev-services
tutorcodejail/patches/local-docker-compose-jobs-services
tutorcodejail/patches/local-docker-compose-services
tutorcodejail/templates/codejail/apps/.gitignore
tutorcodejail/templates/codejail/apps/codejail/tutor.py
tutorcodejail/templates/codejail/apps/codejail-service-v2/tutor.py
tutorcodejail/templates/codejail/apps/profiles/docker-edx-sandbox.profile
tutorcodejail/templates/codejail/apps/profiles/openedx-codejail-service.profile
tutorcodejail/templates/codejail/build/.gitignore
tutorcodejail/templates/codejail/build/codejail/Dockerfile
tutorcodejail/templates/codejail/build/codejail-service/Dockerfile
tutorcodejail/templates/codejail/build/codejail_apparmor/Dockerfile
tutor_contrib_codejail-21.0.0.dist-info/METADATA
tutor_contrib_codejail-21.0.0.dist-info/WHEEL
tutor_contrib_codejail-21.0.0.dist-info/entry_points.txt
tutor_contrib_codejail-21.0.0.dist-info/top_level.txt
tutor_contrib_codejail-21.0.0.dist-info/RECORD
