Metadata-Version: 2.4
Name: tutor-contrib-codejail
Version: 21.0.0
Summary: Codejail plugin for Tutor
Home-page: https://github.com/github/tutor-contrib-codejail
Author: eduNEXT
License: AGPLv3
Project-URL: Code, https://github.com/edunext/tutor-contrib-codejail
Project-URL: Issue tracker, https://github.com/edunext/tutor-contrib-codejail/issues
Classifier: Development Status :: 3 - Alpha
Classifier: Intended Audience :: Developers
Classifier: License :: OSI Approved :: GNU Affero General Public License v3
Classifier: Operating System :: OS Independent
Classifier: Programming Language :: Python
Classifier: Programming Language :: Python :: 3.10
Classifier: Programming Language :: Python :: 3.11
Classifier: Programming Language :: Python :: 3.12
Requires-Python: >=3.10
License-File: LICENSE
Requires-Dist: tutor~=21.0
Dynamic: author
Dynamic: classifier
Dynamic: description
Dynamic: home-page
Dynamic: license
Dynamic: license-file
Dynamic: project-url
Dynamic: requires-dist
Dynamic: requires-python
Dynamic: summary
